gs_pdf_compress/__init__.py
gs_pdf_compress/pdfcompress-qt.py
gs_pdf_compress/pdfcompress.py
gs_pdf_compress/qhinttextcombobox.py
gs_pdf_compress/res/icon.svg
gs_pdf_compress/res/pdfcompress-qt.ui
gs_pdf_compress-0.1.dist-info/METADATA
gs_pdf_compress-0.1.dist-info/WHEEL
gs_pdf_compress-0.1.dist-info/entry_points.txt
gs_pdf_compress-0.1.dist-info/licenses/LICENSE.txt
gs_pdf_compress-0.1.dist-info/RECORD
