Metadata-Version: 2.4
Name: gs-pdf-compress
Version: 0.1
Summary: Compress PDF files with Ghostscript
Project-URL: Homepage, https://github.com/clorteau/pdfcompress
Project-URL: Issues, https://github.com/clorteau/pdfcompress/issues
Author-email: Clem Lorteau <spam@lorteau.fr>
License-Expression: MIT
License-File: LICENSE.txt
Keywords: compression,ghostscript,pdf,python,qt,qt6
Classifier: Operating System :: OS Independent
Classifier: Programming Language :: Python :: 3
Requires-Python: >=3.8
Requires-Dist: pyqt6
